soket/Q1_error_crc.py
soket/Q2_distancevectoralgorithm.py
soket/Q3_Dijkstra.py
soket/Q4_leakybucket.py
soket/Q5_tcpip.py
soket/Q6_udpsocket.py
soket/__init__.py
soket/main.py
soket-1.dist-info/LICENSE
soket-1.dist-info/METADATA
soket-1.dist-info/WHEEL
soket-1.dist-info/top_level.txt
soket-1.dist-info/RECORD
